{
  "user": [
    {
      "id": 1,
      "name": "Leanne Graham",
      "email": "Sincere@april.biz",
      "address": "London",
      "contact": "1-770-736-8031 x56442"
    },
    {
      "id": 2,
      "name": "Ervin Howell",
      "email": "Shanna@melissa.tv",
      "address": "Japan",
      "contact": "010-692-6593 x09125"
    },
    {
      "name": "Sam",
      "email": "sam@gmail.com",
      "contact": "79886546594",
      "address": "Sandiego",
      "id": 3
    },
    {
      "name": "Larry",
      "email": "lary2@gmail.com",
      "contact": "7861321",
      "address": "UK",
      "id": 4
    }
  ]
}